fb_idb-1.1.7.data/data/protoc_compiler_template.py
fb_idb-1.1.7.data/data/proto/idb.proto
idb/__init__.py
idb/cli/__init__.py
idb/cli/main.py
idb/cli/commands/__init__.py
idb/cli/commands/accessibility.py
idb/cli/commands/app.py
idb/cli/commands/approve.py
idb/cli/commands/contacts.py
idb/cli/commands/crash.py
idb/cli/commands/daemon.py
idb/cli/commands/dap.py
idb/cli/commands/debugserver.py
idb/cli/commands/dsym.py
idb/cli/commands/dylib.py
idb/cli/commands/file.py
idb/cli/commands/focus.py
idb/cli/commands/framework.py
idb/cli/commands/hid.py
idb/cli/commands/instruments.py
idb/cli/commands/keychain.py
idb/cli/commands/kill.py
idb/cli/commands/launch.py
idb/cli/commands/location.py
idb/cli/commands/log.py
idb/cli/commands/media.py
idb/cli/commands/memory.py
idb/cli/commands/notification.py
idb/cli/commands/screenshot.py
idb/cli/commands/settings.py
idb/cli/commands/shell.py
idb/cli/commands/target.py
idb/cli/commands/url.py
idb/cli/commands/video.py
idb/cli/commands/xctest.py
idb/cli/commands/xctrace.py
idb/cli/tests/__init__.py
idb/cli/tests/connect_tests.py
idb/cli/tests/parser_tests.py
idb/client/__init__.py
idb/common/__init__.py
idb/common/args.py
idb/common/command.py
idb/common/companion.py
idb/common/companion_set.py
idb/common/companion_spawner.py
idb/common/constants.py
idb/common/direct_companion_manager.py
idb/common/file.py
idb/common/format.py
idb/common/gzip.py
idb/common/hid.py
idb/common/local_targets_manager.py
idb/common/logging.py
idb/common/misc.py
idb/common/networking.py
idb/common/pid_saver.py
idb/common/plugin.py
idb/common/signal.py
idb/common/socket.py
idb/common/stream.py
idb/common/tar.py
idb/common/types.py
idb/common/udid.py
idb/common/tests/__init__.py
idb/common/tests/companion_set_tests.py
idb/common/tests/companion_spawner_tests.py
idb/common/tests/companion_tests.py
idb/common/tests/direct_companion_manager_tests.py
idb/common/tests/format_tests.py
idb/common/tests/local_targets_manager_tests.py
fb_idb-1.1.7.dist-info/LICENSE
fb_idb-1.1.7.dist-info/METADATA
fb_idb-1.1.7.dist-info/WHEEL
fb_idb-1.1.7.dist-info/entry_points.txt
fb_idb-1.1.7.dist-info/top_level.txt
fb_idb-1.1.7.dist-info/RECORD
