Metadata-Version: 2.1
Name: fb-idb
Version: 1.1.7
Summary: iOS debug bridge
Home-page: https://github.com/facebook/idb
Author: Facebook
Author-email: callumryan@fb.com
License: MIT
Platform: UNKNOWN
Classifier: Programming Language :: Python :: 3.6
Classifier: License :: OSI Approved :: MIT License
Classifier: Operating System :: OS Independent
Requires-Python: >=3.7
